prose/__init__.py
prose/archive/__init__.py
prose/archive/pos1.py
prose/archive/sdss.py
prose/blocks/__init__.py
prose/blocks/alignment.py
prose/blocks/background.py
prose/blocks/catalogs.py
prose/blocks/centroids.py
prose/blocks/detection.py
prose/blocks/geometry.py
prose/blocks/photometry.py
prose/blocks/psf.py
prose/blocks/shepard.py
prose/blocks/utils.py
prose/blocks/visualization.py
prose/builtins.py
prose/citations.py
prose/config.py
prose/console_utils.py
prose/core/__init__.py
prose/core/block.py
prose/core/image.py
prose/core/sequence.py
prose/core/source.py
prose/fluxes.py
prose/io/__init__.py
prose/io/create_fm_db.sql
prose/io/fitsmanager.py
prose/io/io.py
prose/scripts/fitsmanager.py
prose/simulations.py
prose/telescope.py
prose/utils.py
prose/visualization.py
prose-3.3.4.dist-info/LICENSE
prose-3.3.4.dist-info/METADATA
prose-3.3.4.dist-info/WHEEL
prose-3.3.4.dist-info/entry_points.txt
prose-3.3.4.dist-info/RECORD
