Metadata-Version: 2.1
Name: prose
Version: 3.3.4
Summary: Modular image processing pipelines for Astronomy
License: MIT
Author: Lionel Garcia
Requires-Python: >=3.9,<3.12
Classifier: License :: OSI Approved :: MIT License
Classifier: Programming Language :: Python :: 3
Classifier: Programming Language :: Python :: 3.9
Classifier: Programming Language :: Python :: 3.10
Classifier: Programming Language :: Python :: 3.11
Requires-Dist: astropy (>=5.1.1,<6.0.0)
Requires-Dist: astroquery (>=0.4.6,<0.5.0)
Requires-Dist: celerite2
Requires-Dist: imageio[ffmpeg]
Requires-Dist: ipython
Requires-Dist: matplotlib
Requires-Dist: multiprocess
Requires-Dist: numpy (>=1.23.5,<2.0.0)
Requires-Dist: pandas (>1.1)
Requires-Dist: photutils (>=1.6.0,<2.0.0)
Requires-Dist: pytest
Requires-Dist: pyyaml
Requires-Dist: requests (>=2.31.0,<3.0.0)
Requires-Dist: scikit-image (>=0.21.0,<0.22.0)
Requires-Dist: scipy
Requires-Dist: sep
Requires-Dist: tabulate
Requires-Dist: tqdm
Requires-Dist: twirl (==0.4.0)
